dwave/cloud/__init__.py
dwave/cloud/cli.py
dwave/cloud/coders.py
dwave/cloud/computation.py
dwave/cloud/concurrency.py
dwave/cloud/events.py
dwave/cloud/exceptions.py
dwave/cloud/package_info.py
dwave/cloud/regions.py
dwave/cloud/solver.py
dwave/cloud/upload.py
dwave/cloud/api/__init__.py
dwave/cloud/api/client.py
dwave/cloud/api/constants.py
dwave/cloud/api/exceptions.py
dwave/cloud/api/models.py
dwave/cloud/api/resources.py
dwave/cloud/auth/__init__.py
dwave/cloud/auth/_creds.py
dwave/cloud/auth/config.py
dwave/cloud/auth/creds.py
dwave/cloud/auth/flows.py
dwave/cloud/auth/server.py
dwave/cloud/client/__init__.py
dwave/cloud/client/base.py
dwave/cloud/client/hybrid.py
dwave/cloud/client/qpu.py
dwave/cloud/client/sw.py
dwave/cloud/config/__init__.py
dwave/cloud/config/constants.py
dwave/cloud/config/exceptions.py
dwave/cloud/config/loaders.py
dwave/cloud/config/models.py
dwave/cloud/testing/__init__.py
dwave/cloud/testing/mocks.py
dwave/cloud/utils/__init__.py
dwave/cloud/utils/cli.py
dwave/cloud/utils/coders.py
dwave/cloud/utils/decorators.py
dwave/cloud/utils/dist.py
dwave/cloud/utils/exception.py
dwave/cloud/utils/http.py
dwave/cloud/utils/logging.py
dwave/cloud/utils/qubo.py
dwave/cloud/utils/time.py
dwave_cloud_client-0.14.3.dist-info/licenses/LICENSE
dwave_cloud_client-0.14.3.dist-info/METADATA
dwave_cloud_client-0.14.3.dist-info/WHEEL
dwave_cloud_client-0.14.3.dist-info/entry_points.txt
dwave_cloud_client-0.14.3.dist-info/top_level.txt
dwave_cloud_client-0.14.3.dist-info/RECORD
