Metadata-Version: 2.4
Name: dwave-cloud-client
Version: 0.14.3
Summary: A minimal client for interacting with D-Wave cloud resources.
Home-page: https://github.com/dwavesystems/dwave-cloud-client
Author: D-Wave Systems Inc.
License: Apache 2.0
Classifier: License :: OSI Approved :: Apache Software License
Classifier: Operating System :: OS Independent
Classifier: Programming Language :: Python :: 3
Classifier: Programming Language :: Python :: 3.10
Classifier: Programming Language :: Python :: 3.11
Classifier: Programming Language :: Python :: 3.12
Classifier: Programming Language :: Python :: 3.13
Classifier: Programming Language :: Python :: 3.14
Requires-Python: >=3.10
License-File: LICENSE
Requires-Dist: requests[socks]<3,>=2.25
Requires-Dist: urllib3<3,>=1.26
Requires-Dist: pydantic<3,>=2
Requires-Dist: homebase<2,>=1.0
Requires-Dist: click<9,>=8.2
Requires-Dist: python-dateutil<3,>=2.7
Requires-Dist: plucky<0.5,>=0.4.3
Requires-Dist: diskcache<6,>=5.2.1
Requires-Dist: packaging>=19
Requires-Dist: werkzeug<4,>=3.1.0
Requires-Dist: typing-extensions<5,>=4.5.0
Requires-Dist: authlib<2,>=1.2
Requires-Dist: importlib_metadata>=5.0.0
Requires-Dist: orjson>=3.11
Requires-Dist: http-sf>=1.0.4
Provides-Extra: test
Requires-Dist: requests_mock; extra == "test"
Requires-Dist: mock; extra == "test"
Requires-Dist: numpy; extra == "test"
Requires-Dist: coverage; extra == "test"
Provides-Extra: bqm
Requires-Dist: dimod!=0.11.4,<0.13,>=0.10.5; extra == "bqm"
Requires-Dist: numpy>=1.17.3; extra == "bqm"
Provides-Extra: dqm
Requires-Dist: dimod!=0.11.4,<0.13,>=0.10.5; extra == "dqm"
Requires-Dist: numpy>=1.17.3; extra == "dqm"
Provides-Extra: cqm
Requires-Dist: dimod!=0.11.4,<0.13,>=0.10.5; extra == "cqm"
Requires-Dist: numpy>=1.17.3; extra == "cqm"
Provides-Extra: nlm
Requires-Dist: dwave-optimization<0.5,>=0.1.0; extra == "nlm"
Requires-Dist: numpy>=1.20.0; extra == "nlm"
Provides-Extra: mocks
Requires-Dist: dwave-networkx>=0.8.10; extra == "mocks"
Dynamic: author
Dynamic: classifier
Dynamic: description
Dynamic: home-page
Dynamic: license
Dynamic: license-file
Dynamic: provides-extra
Dynamic: requires-dist
Dynamic: requires-python
Dynamic: summary
